{
    "meta": {
        "num_tuples": 33845,
        "num_attributes": 5,
        "num_attributes_in_BN": 3,
        "all_attributes": [
            "Unnamed: 0",
            "DESTPORT",
            "PROTOCOL",
            "SERVICE",
            "INDEX_COLUMN"
        ],
        "candidate_keys": [
            "Unnamed: 0",
            "INDEX_COLUMN"
        ],
        "non_categorical_string_attributes": [],
        "attributes_in_BN": [
            "DESTPORT",
            "PROTOCOL",
            "SERVICE"
        ]
    },
    "attribute_description": {
        "Unnamed: 0": {
            "name": "Unnamed: 0",
            "data_type": "Integer",
            "is_categorical": false,
            "is_candidate_key": true,
            "min": 0,
            "max": 33844,
            "missing_rate": 0.0,
            "distribution_bins": [
                0.0,
                1692.2,
                3384.4,
                5076.6,
                6768.8,
                8461.0,
                10153.2,
                11845.4,
                13537.6,
                15229.800000000001,
                16922.0,
                18614.2,
                20306.4,
                21998.600000000002,
                23690.8,
                25383.0,
                27075.2,
                28767.4,
                30459.600000000002,
                32151.8
            ],
            "distribution_probabilities": [
                0.050130793780930535,
                0.05078160292612148,
                0.050167060260850826,
                0.049889766148438194,
                0.049959020244820115,
                0.05021469158270531,
                0.04925611996048757,
                0.05015066567702038,
                0.050154809837493375,
                0.04969973743258802,
                0.04955562102276958,
                0.04984337527138333,
                0.04989388827038215,
                0.050060410678910136,
                0.049960291683803136,
                0.051370305047967274,
                0.04944313695643006,
                0.049697189854794314,
                0.04960553938294893,
                0.05016597397915524
            ]
        },
        "DESTPORT": {
            "name": "DESTPORT",
            "data_type": "Integer",
            "is_categorical": true,
            "is_candidate_key": false,
            "min": 21,
            "max": 10051,
            "missing_rate": 0.0,
            "distribution_bins": [
                21,
                22,
                23,
                53,
                80,
                137,
                138,
                161,
                443,
                445,
                500,
                587,
                993,
                1344,
                1433,
                3128,
                3389,
                3689,
                5060,
                5061,
                5222,
                5432,
                5900,
                6969,
                8000,
                8080,
                9100,
                10001,
                10051
            ],
            "distribution_probabilities": [
                0.06322580112346844,
                0.0023138042880329313,
                0.0,
                0.12774140084705696,
                0.07713984366812242,
                0.0001627861357829322,
                0.0,
                0.0038127104999031354,
                0.6761272717174168,
                0.0005128961669581599,
                0.0,
                0.0004594298511257184,
                0.0014863082222549477,
                0.0014111608150418511,
                6.601561932454805e-06,
                0.015654458930791315,
                0.00014280088954278462,
                0.00026089050943352873,
                0.000338801132513751,
                0.0,
                0.016929397927532935,
                0.0,
                0.0,
                0.0058780942719513524,
                0.00011079306040272336,
                0.0004250574883380089,
                0.001297544049206778,
                0.0006428264068793543,
                0.0039193204363107415
            ]
        },
        "PROTOCOL": {
            "name": "PROTOCOL",
            "data_type": "String",
            "is_categorical": true,
            "is_candidate_key": false,
            "min": 3,
            "max": 3,
            "missing_rate": 0.0,
            "distribution_bins": [
                "TCP",
                "UDP"
            ],
            "distribution_probabilities": [
                0.8290657853224563,
                0.1709342146775437
            ]
        },
        "SERVICE": {
            "name": "SERVICE",
            "data_type": "String",
            "is_categorical": true,
            "is_candidate_key": false,
            "min": 3,
            "max": 9,
            "missing_rate": 0.0,
            "distribution_bins": [
                "ACMSODA",
                "DAAPD",
                "DNS",
                "EMS",
                "FTP",
                "HPSERVICE",
                "HTTP",
                "HTTPS",
                "ICAP",
                "IMAP4",
                "IRDMI",
                "ISAKMP",
                "MDS",
                "MSSQL",
                "NETBIOS",
                "PGSQL",
                "RDP",
                "SIP",
                "SNMP",
                "SSH",
                "TELNET",
                "UBIQUITY",
                "VNC",
                "XMPP",
                "ZABBIX"
            ],
            "distribution_probabilities": [
                0.006076827744538799,
                0.0007220227100625921,
                0.12755656555361128,
                0.00020334231234639012,
                0.06278123386844792,
                0.0013217527048916303,
                0.09288668733124576,
                0.6735987329260457,
                0.0003917862542659501,
                0.0009274937759504136,
                0.0005567446703977107,
                0.0,
                0.00030310365951969107,
                0.0,
                0.0002840298748791849,
                0.0009436052787268175,
                0.0,
                0.0013271076842608044,
                0.004202369535522475,
                0.0023859490499191028,
                0.0,
                0.0014252524834259324,
                0.0,
                0.01779481474434711,
                0.004310577837594822
            ]
        },
        "INDEX_COLUMN": {
            "name": "INDEX_COLUMN",
            "data_type": "Integer",
            "is_categorical": false,
            "is_candidate_key": true,
            "min": 0,
            "max": 33844,
            "missing_rate": 0.0,
            "distribution_bins": [
                0.0,
                1692.2,
                3384.4,
                5076.6,
                6768.8,
                8461.0,
                10153.2,
                11845.4,
                13537.6,
                15229.800000000001,
                16922.0,
                18614.2,
                20306.4,
                21998.600000000002,
                23690.8,
                25383.0,
                27075.2,
                28767.4,
                30459.600000000002,
                32151.8
            ],
            "distribution_probabilities": [
                0.049800720608031895,
                0.050305178854350985,
                0.04987305112699251,
                0.05046410629903861,
                0.05001806517789055,
                0.05049551942889718,
                0.050127487338535025,
                0.05016735455496359,
                0.04995615742675762,
                0.05081697042799309,
                0.05010507743586711,
                0.049896682783008094,
                0.05003998420056604,
                0.04880020629566278,
                0.04977609110114586,
                0.05012156024067256,
                0.04976231988770263,
                0.050050603116655906,
                0.0499007663863555,
                0.049522097308912404
            ]
        }
    },
    "bayesian_network": [
        [
            "SERVICE",
            [
                "PROTOCOL"
            ]
        ],
        [
            "DESTPORT",
            [
                "SERVICE",
                "PROTOCOL"
            ]
        ]
    ],
    "conditional_probabilities": {
        "PROTOCOL": [
            0.7993303645198199,
            0.20066963548018016
        ],
        "SERVICE": {
            "[0]": [
                0.0038029295000451472,
                0.0013532235650177528,
                0.007340887196276189,
                0.002106801957169187,
                0.07436743475389486,
                0.0036320394477186925,
                0.10526553394850435,
                0.7368834210642999,
                0.0016381983378452314,
                0.005442997787474598,
                0.002091330052249867,
                0.0010537626347420462,
                0.0020953679781884967,
                0.0023674901329530785,
                0.0018193271435022593,
                0.003040944829499572,
                0.0029910645135941775,
                0.0011679080814274037,
                0.0015348397283320968,
                0.0057449947579207485,
                0.002114563026400189,
                0.0029669826300079277,
                0.0021266697175677954,
                0.020899725090364155,
                0.006151562125004425
            ],
            "[1]": [
                0.030953435829141684,
                0.010293763845562123,
                0.5679709484319296,
                0.005081371100597252,
                0.009665910611058506,
                0.005782579390739001,
                0.019094895707063367,
                0.16603925345065382,
                0.012205593717151268,
                0.004739732370035508,
                0.009157654948410735,
                0.009120849340867465,
                0.010696083906393329,
                0.01265605182451514,
                0.00596956277641875,
                0.010209911394566387,
                0.006906993668441818,
                0.016149839897705406,
                0.02936250563731601,
                0.010587488514777104,
                0.013267663246763683,
                0.007759238942190475,
                0.007138329067090299,
                0.009509572977469063,
                0.009680769403142065
            ]
        },
        "DESTPORT": {
            "[0, 0]": [
                0.008209993473573833,
                0.003356206692307077,
                0.0,
                0.012311356400866549,
                0.0,
                0.05460973325647216,
                0.09355463761140825,
                0.0,
                0.03125008400425447,
                0.002124149290785665,
                0.0052200340149900085,
                0.06798152862770701,
                0.0,
                0.0,
                0.0,
                0.039050269095146556,
                0.02899800889902363,
                0.048072092581437936,
                0.11247812147484228,
                0.032546956679870925,
                0.0,
                0.029381672426452485,
                0.0,
                0.35071091935087806,
                0.0,
                0.07854987874959876,
                0.001594357370384438,
                0.0,
                0.0
            ],
            "[0, 1]": [
                0.06420987788605162,
                0.012765369869006483,
                0.0,
                3.717248773768332e-05,
                0.0,
                0.0,
                0.0,
                0.0,
                0.00788884572431383,
                0.0,
                0.0008729625161327016,
                0.0,
                0.0,
                0.0,
                0.049562412754353545,
                0.0,
                0.0,
                0.004467788812471239,
                0.0,
                0.02520031828154689,
                0.010101853876696031,
                0.04714705565240783,
                0.00026874052159345685,
                0.7158285869539979,
                0.0018205686903412827,
                0.03454021732842724,
                0.0007406100627839873,
                0.0,
                0.024547618582138275
            ],
            "[1, 0]": [
                0.07973448950281145,
                0.0,
                0.014760167570743726,
                0.0,
                0.026898849225199997,
                0.02545637671650483,
                0.026715037829892426,
                0.2190915296241009,
                0.04532635714841599,
                0.0,
                0.0,
                0.050437582772000965,
                0.0,
                0.04069070229813982,
                0.041862485479441325,
                0.0,
                0.0,
                0.0,
                0.0,
                0.015170626639093144,
                0.0,
                0.3771933711891145,
                0.0,
                0.0,
                0.0,
                0.036662424004540756,
                0.0,
                0.0,
                0.0
            ],
            "[1, 1]": [
                0.0,
                0.0,
                0.0,
                0.0,
                0.06638967327745458,
                0.0,
                0.0,
                0.0,
                0.07523862080686604,
                0.1159344520105543,
                0.2164317350751629,
                0.0,
                0.14139403813280266,
                0.04602648816551485,
                0.022732830185990708,
                0.0,
                0.0,
                0.0,
                0.0980742554743047,
                0.0,
                0.0,
                0.0,
                0.04267688005575969,
                0.06124285604890763,
                0.0,
                0.0,
                0.06077964839455352,
                0.0530785223721285,
                0.0
            ],
            "[2, 0]": [
                0.0,
                0.0,
                0.006930837138532497,
                0.8080933582819492,
                0.0,
                0.0,
                0.01898845930733915,
                0.0,
                0.020827573975267473,
                0.0,
                0.056490859955045825,
                0.0,
                0.056729249346813115,
                0.00435031810985349,
                0.012036153020174151,
                0.0,
                0.0,
                0.0,
                0.0,
                0.0,
                0.0,
                0.0,
                0.0,
                0.008984944358194056,
                0.002642570306090821,
                0.0,
                0.0008801478235296504,
                0.0,
                0.003045528377210571
            ],
            "[2, 1]": [
                0.0,
                0.0,
                0.0,
                0.9870142440771608,
                0.0,
                0.00013960404177829712,
                0.0,
                0.0002039205972155795,
                0.0,
                0.00288534978641004,
                0.0019066604132937119,
                0.0,
                0.0,
                0.0,
                0.0,
                0.0,
                0.00031186400866037756,
                0.0,
                0.0,
                0.0009176917169823201,
                0.0005152665886612856,
                0.0022776995255203614,
                0.0,
                0.0015086280507759999,
                0.0007389007875565474,
                0.0,
                0.00026536682105699714,
                0.0,
                0.001314803584927807
            ],
            "[3, 0]": [
                0.12599668385880927,
                0.0,
                0.026260651145982482,
                0.0,
                0.036507806002928,
                0.0,
                0.0,
                0.012237093230704635,
                0.0,
                0.06908781249587821,
                0.0,
                0.06051414115984222,
                0.0,
                0.040940893800229854,
                0.16631127230136075,
                0.0,
                0.010643795156493937,
                0.013104195704748972,
                0.010053000000731376,
                0.0,
                0.15195634071860845,
                0.0,
                0.07602618804642461,
                0.032791543813455365,
                0.0,
                0.06362446760790325,
                0.0,
                0.09251817547019318,
                0.011425939485705474
            ],
            "[3, 1]": [
                0.0,
                0.0,
                0.0,
                0.0,
                0.07172656371351764,
                0.005884542018980732,
                0.0,
                0.0,
                0.0,
                0.0,
                0.0,
                0.21285370981891047,
                0.0,
                0.13416038980687658,
                0.09902377003722647,
                0.0,
                0.025267683338263142,
                0.0,
                0.0647200968881351,
                0.03419849108348055,
                0.10402101738913948,
                0.0,
                0.1883267746521967,
                0.0,
                0.0,
                0.05981696125327317,
                0.0,
                0.0,
                0.0
            ],
            "[4, 0]": [
                0.9807049767231996,
                0.0008872661595791176,
                0.0010926003180301933,
                4.839785133336467e-06,
                0.0044384152646031365,
                0.0006197812646994427,
                0.0,
                0.000436585504989596,
                0.0,
                0.0,
                0.0007046751488687807,
                0.0,
                0.0004912777156404763,
                0.0,
                0.0,
                0.0,
                0.00027506748720861865,
                0.0003660148949710858,
                0.0002936641249507282,
                0.0006676127080091555,
                0.000661846810687136,
                0.0,
                0.002874893746303531,
                0.0,
                0.0,
                0.002795116205866959,
                0.0017294220868404684,
                0.0009559440504186616,
                0.0
            ],
            "[4, 1]": [
                0.056313321533092896,
                0.0,
                0.08088336540616532,
                0.03514451471841452,
                0.0,
                0.0,
                0.001777028503378626,
                0.08419892624974441,
                0.035987329274102996,
                0.0,
                0.027488413521677073,
                0.1021404612505988,
                0.03055082241535985,
                0.0,
                0.0,
                0.0,
                0.0,
                0.1159473291934654,
                0.10484337646368955,
                0.0,
                0.0,
                0.012508661222758833,
                0.1459055815750432,
                0.0,
                0.0,
                0.07688400666670112,
                0.0,
                0.08942686200580725,
                0.0
            ],
            "[5, 0]": [
                0.06822949350669093,
                0.02090299844659121,
                0.22687606124176266,
                0.0,
                0.049795689697876656,
                0.0,
                0.009819659388069123,
                0.0,
                0.04449092504701798,
                0.035628105300904246,
                0.005557108253546233,
                0.0,
                0.0,
                0.018767006691654372,
                0.0,
                0.02193894355916259,
                0.049304889981305326,
                0.11271654938420551,
                0.04645801357096021,
                0.0,
                0.0,
                0.023021126199214217,
                0.0,
                0.0016059993212564194,
                0.0,
                0.0,
                0.23181144141116353,
                0.033075988998618744,
                0.0
            ],
            "[5, 1]": [
                0.00631630556543358,
                0.0,
                0.0,
                0.0,
                0.0,
                0.0,
                0.165608164111951,
                0.058206134322475685,
                0.05675486774082057,
                0.0,
                0.015789911318632423,
                0.07639621971590368,
                0.08361506714256019,
                0.0,
                0.07294432621547088,
                0.05966348001291138,
                0.0,
                0.12305181606574477,
                0.0,
                0.0,
                0.0,
                0.013631640585801791,
                0.025942086671084896,
                0.0,
                0.12364156433240021,
                0.02757636822454943,
                0.0,
                0.0,
                0.09086204797425941
            ],
            "[6, 0]": [
                0.0,
                0.002499755326043289,
                0.0006776415078584343,
                0.0,
                0.8178235452148561,
                0.00035881566964833067,
                0.0002162891196993299,
                0.0,
                0.00261465644238747,
                0.0003334807315553452,
                9.531010494965158e-05,
                0.0002555501078556121,
                0.0007949394738727525,
                0.0,
                0.0,
                0.15744621839793105,
                0.0,
                0.0028308823372746664,
                0.0008407843022952003,
                0.0,
                0.0,
                0.0,
                0.0,
                0.0,
                0.0,
                0.013212131263772861,
                0.0,
                0.0,
                0.0
            ],
            "[6, 1]": [
                0.0,
                0.0,
                0.0,
                0.03947745294331117,
                0.6316926382655813,
                0.0,
                0.0,
                0.0,
                0.0,
                0.04552311025003874,
                0.0,
                0.09181752120062334,
                0.0,
                0.03674639993606578,
                0.004040486354538814,
                0.0,
                0.0,
                0.02046837225074965,
                0.0,
                0.010695182318158502,
                0.0009983508043297528,
                0.0,
                0.04589172823044462,
                0.003276329604030155,
                0.030021664119685328,
                0.0169829830643953,
                0.0,
                0.022367780658047526,
                0.0
            ],
            "[7, 0]": [
                0.0,
                8.183830268004914e-05,
                0.0,
                1.3990981579575659e-05,
                0.00029036091044152846,
                0.0007267813250536004,
                0.0,
                7.269778265927737e-05,
                0.9969143764082777,
                0.0,
                0.000133926520702153,
                0.0,
                0.0,
                3.5792017703155665e-05,
                0.00019981093034072462,
                5.494490440960733e-05,
                0.00025186838231566007,
                0.0,
                0.00016695271390348168,
                0.0,
                0.0004346202375752595,
                8.654811101284652e-05,
                0.0,
                0.0004146014235217934,
                0.00011406037173337378,
                0.0,
                0.0,
                6.828676090125273e-06,
                0.0
            ],
            "[7, 1]": [
                0.005343785341386133,
                0.0,
                0.0,
                0.0,
                0.0,
                0.0033264374804594437,
                0.0,
                0.0,
                0.9655467868799806,
                0.0032171857342260563,
                0.0,
                0.0,
                0.0,
                0.0017255774774043772,
                0.0,
                0.0,
                0.0018716933986175008,
                0.0,
                0.0019792590091582394,
                0.00324034383635424,
                0.0,
                0.009602433829360855,
                0.0,
                0.0,
                0.0,
                0.0,
                0.0,
                0.00014768897499322224,
                0.003998808038059246
            ],
            "[8, 0]": [
                0.0,
                0.0,
                0.0,
                0.0,
                0.0,
                0.01579188290702556,
                0.10776174462398214,
                0.0,
                0.002930489067021766,
                0.0,
                0.04710643430578896,
                0.0,
                0.01161629411381157,
                0.1446667013294966,
                0.0,
                0.0,
                0.0,
                0.17623436861633984,
                0.06265839084068454,
                0.056976472967590425,
                0.13646078250737276,
                0.0,
                0.009132308934272146,
                0.015330433165822104,
                0.2133336966207916,
                0.0,
                0.0,
                0.0,
                0.0
            ],
            "[8, 1]": [
                0.06683434787348601,
                0.0,
                0.012492539900351703,
                0.0,
                0.0,
                0.0,
                0.0,
                0.0,
                0.02726072908413269,
                0.0,
                0.06289856168091783,
                0.028085698297331218,
                0.0,
                0.09328490701630518,
                0.0005626571822018632,
                0.3484444069874295,
                0.0,
                0.0032051907863052853,
                0.0,
                0.0,
                0.008904011691648723,
                0.08212143253141038,
                0.0417609167118465,
                0.02630621177127373,
                0.005578264945162992,
                0.0824504643951305,
                0.0,
                0.060982887884282494,
                0.04882677126078343
            ],
            "[9, 0]": [
                0.04885143073948629,
                0.01035319707078757,
                0.021059336295897017,
                0.0,
                0.004730372734103261,
                0.0,
                0.0,
                0.07731009157639006,
                0.034864706630381485,
                0.0,
                0.06396906862380987,
                0.0,
                0.4933744992051044,
                0.053440897978476135,
                0.022745467668706627,
                0.007537259684771795,
                0.03442104328720083,
                0.0,
                0.02984209625811788,
                0.00670325184070215,
                0.0,
                0.0,
                0.0,
                0.0826436236205406,
                0.0,
                0.0,
                0.008153656785523933,
                0.0,
                0.0
            ],
            "[9, 1]": [
                0.0,
                0.08916939967347916,
                0.0,
                0.0,
                0.0,
                0.0015762306329065964,
                0.07320576201596707,
                0.0,
                0.0034554631265440463,
                0.2388287834942177,
                0.0,
                0.0498829744308227,
                0.023436574766881255,
                0.0,
                0.0,
                0.06164150503198421,
                0.0,
                0.16230326790342495,
                0.004674937597515311,
                0.0,
                0.0,
                0.2713091245006715,
                0.020515976825585498,
                0.0,
                0.0,
                0.0,
                0.0,
                0.0,
                0.0
            ],
            "[10, 0]": [
                0.0670612945461911,
                0.0,
                0.001485824176705405,
                0.0,
                0.0,
                0.08362451978597589,
                0.1892012758511078,
                0.16525887953868795,
                0.10883349435012626,
                0.05153974683729666,
                0.0,
                0.0,
                0.0,
                0.0,
                0.0,
                0.0,
                0.03893310010489301,
                0.0,
                0.050551782773866405,
                0.0,
                0.0,
                0.0,
                0.0273660623028219,
                0.0,
                0.08610241735101669,
                0.007908028107173549,
                0.08285670911878451,
                0.039276865155352746,
                0.0
            ],
            "[10, 1]": [
                0.0,
                0.011518333884669192,
                0.041684369164576504,
                0.0,
                0.0162768675384881,
                0.019328681091585087,
                0.13421597654334694,
                0.0479992538144217,
                0.07041922803935177,
                0.0,
                0.0,
                0.28233593053138195,
                0.0,
                0.0,
                0.0,
                0.12906809281805867,
                0.15684150953972792,
                0.03409625477848875,
                0.0,
                0.0,
                0.0,
                0.0,
                0.003128297826015169,
                0.0,
                0.0,
                0.017250211114429346,
                0.03583699331545879,
                0.0,
                0.0
            ],
            "[11, 0]": [
                0.0,
                0.0,
                0.0,
                0.0,
                0.0,
                0.058800015552859373,
                0.0639196296487796,
                0.0,
                0.0,
                0.0,
                0.11082749783165227,
                0.0,
                0.06450134264490372,
                0.10496412905146348,
                0.10421689626474956,
                0.0,
                0.0,
                0.024804682658288873,
                0.0,
                0.0,
                0.0,
                0.0,
                0.0,
                0.11786818244315861,
                0.0,
                0.004944899451277569,
                0.0,
                0.021701976564332925,
                0.323450747888534
            ],
            "[11, 1]": [
                0.02149923665318121,
                0.07265016587588867,
                0.0,
                0.16518873711383164,
                0.0,
                0.0,
                0.0,
                0.0,
                0.0617851517719967,
                0.0,
                0.1644009739108897,
                0.051759944704958726,
                0.033343844076865546,
                0.007314154550645298,
                0.031259786751520705,
                0.0,
                0.0,
                0.0,
                0.0013452747744261138,
                0.0,
                0.0,
                0.15848271746555648,
                0.07502176110395983,
                0.0,
                0.0,
                0.1273283796462745,
                0.0,
                0.0,
                0.028619871600004867
            ],
            "[12, 0]": [
                0.02228494578926575,
                0.0,
                0.0,
                0.0013106230966686663,
                0.004864128475415126,
                0.029185501876020734,
                0.0,
                0.0,
                0.0,
                0.23895630470327486,
                0.0,
                0.10686559206191816,
                0.0059381437237806265,
                0.0,
                0.09353610156366633,
                0.0,
                0.038522218845472335,
                0.0,
                0.10690637066332974,
                0.03096444325317066,
                0.03300125704486109,
                0.0,
                0.04667083444348091,
                0.020570274117518522,
                0.0,
                0.0,
                0.058184002908055546,
                0.162239257434101,
                0.0
            ],
            "[12, 1]": [
                0.0,
                0.0,
                0.151587157634221,
                0.016526258758799595,
                0.002134434228301844,
                0.0,
                0.0402422383652772,
                0.0,
                0.13788470217508864,
                0.06473891624479075,
                0.013558575762714093,
                0.0,
                0.025959953745967816,
                0.08853953644078719,
                0.0025472332044509287,
                0.0,
                0.0,
                0.036030186400871966,
                0.07428265630814805,
                0.0,
                0.03687924715427337,
                0.0,
                0.13744889070193872,
                0.01321621455426425,
                0.005599269461169676,
                0.0,
                0.09885268367945113,
                0.0,
                0.05397184517948377
            ],
            "[13, 0]": [
                0.011512844345581525,
                0.07204072971828443,
                0.0,
                0.13417299609113106,
                0.009416886206007212,
                0.0588052440455781,
                0.09755949681382023,
                0.057152473794358866,
                0.0,
                0.017088766734007336,
                0.0,
                0.0,
                0.0,
                0.0,
                0.08297453509211623,
                0.0,
                0.14333374104802296,
                0.0,
                0.0,
                0.0,
                0.0,
                0.0,
                0.1121191095575812,
                0.0,
                0.1268347935658368,
                0.07698838298767405,
                0.0,
                0.0,
                0.0
            ],
            "[13, 1]": [
                0.15007796438540286,
                0.03572918370490331,
                0.0016537511623484335,
                0.0,
                0.0,
                0.0,
                0.0,
                0.0,
                0.0,
                0.0,
                0.0,
                0.0,
                0.0019274448305043209,
                0.0,
                0.07148816707552125,
                0.0427813086711802,
                0.004745722998322779,
                0.05194056930273844,
                0.11051267004852415,
                0.0,
                0.012956523167459436,
                0.23569729570259915,
                0.1589053338764553,
                0.009886907364078929,
                0.0,
                0.007772673383814124,
                0.0,
                0.0,
                0.10392448432614718
            ],
            "[14, 0]": [
                0.019391491661704417,
                0.0,
                0.0,
                0.0,
                0.0,
                0.0,
                0.0,
                0.0,
                0.0,
                0.0,
                0.0,
                0.02017245714469912,
                0.2212640768422977,
                0.29441553544778215,
                0.0,
                0.0,
                0.02424691377334567,
                0.0,
                0.28751930945428067,
                0.0,
                0.06234147639665818,
                0.0,
                0.0,
                0.029317950833426247,
                0.0,
                0.03006304682851689,
                0.0026278260823145716,
                0.0,
                0.008639915534974394
            ],
            "[14, 1]": [
                0.0,
                0.029342249649475863,
                0.0,
                0.2046396697024333,
                0.05531402753020644,
                0.0,
                0.10195321034430582,
                0.0,
                0.0,
                0.0,
                0.04147228773334655,
                0.0,
                0.0,
                0.0,
                0.0011560603595284285,
                0.0,
                0.048211547929791536,
                0.0,
                0.028246307236570484,
                0.0,
                0.0,
                0.08308659476899363,
                0.21919226327516864,
                0.0,
                0.09600111791163007,
                0.0,
                0.028245003881921586,
                0.06313965967662752,
                0.0
            ],
            "[15, 0]": [
                0.0,
                0.02378462462017244,
                0.0,
                0.0,
                0.04779104372650771,
                0.08463989331256594,
                0.0,
                0.0,
                0.0,
                0.04436073562296281,
                0.15796774281393808,
                0.1240453693781203,
                0.07408639529136558,
                0.0,
                0.18459587098297078,
                0.0,
                0.0,
                0.10361199951496364,
                0.0,
                0.021299151703446054,
                0.0,
                0.03877118245276224,
                0.06432985450868514,
                0.0,
                0.0,
                0.0,
                0.030716136071539182,
                0.0,
                0.0
            ],
            "[15, 1]": [
                0.0,
                0.0814824675018401,
                0.0,
                0.0,
                0.01058232819120314,
                0.0,
                0.04816577628962468,
                0.09936095797692725,
                0.0,
                0.0,
                0.0,
                0.01026851767981934,
                0.1817510177662764,
                0.026575819120971067,
                0.0,
                0.0,
                0.11650175568476596,
                0.0,
                0.030747903001694055,
                0.10071973033350687,
                0.021149852852119466,
                0.0,
                0.0,
                0.0,
                0.028271718034635376,
                0.018813204149395853,
                0.10258387600470577,
                0.07005554505311083,
                0.05296953035940397
            ],
            "[16, 0]": [
                0.0,
                0.0,
                0.05146621953685956,
                0.0,
                0.0002173367446722209,
                0.09819222959649124,
                0.014153855673896747,
                0.060179806413733154,
                0.09635414591438583,
                0.0315867637558586,
                0.023111687458406246,
                0.12466618102766144,
                0.20379902912142975,
                0.0,
                0.0,
                0.0,
                0.0,
                0.0,
                0.0,
                0.010593390279850852,
                0.0,
                0.07097286190734314,
                0.12442479061588013,
                0.004467168925391769,
                0.0,
                0.009251107080953763,
                0.07157325182533326,
                0.0,
                0.004990174121852287
            ],
            "[16, 1]": [
                0.13547376252915536,
                0.0,
                0.0,
                0.0,
                0.010084553666188956,
                0.03209723822489336,
                0.0,
                0.0,
                0.0,
                0.0,
                0.16883677060108554,
                0.11727243179303073,
                0.09979743850993023,
                0.028587385979104426,
                0.0,
                0.008045747612931684,
                0.07790644037783322,
                0.0,
                0.07213157462153039,
                0.0,
                0.07841464588911877,
                0.0747270087347233,
                0.0,
                0.022966524327746544,
                0.0003849051006874514,
                0.0,
                0.0,
                0.061888823514441325,
                0.011384748517598698
            ],
            "[17, 0]": [
                0.0,
                0.0,
                0.0,
                0.0,
                0.0013713298255587283,
                0.0,
                0.0,
                0.005952708174243726,
                0.08081595421738945,
                0.0,
                0.219136652883502,
                0.14985050667325245,
                0.0,
                0.0,
                0.0,
                0.0,
                0.0,
                0.07602548097440967,
                0.05204254176167526,
                0.061667447816529615,
                0.06350556676787533,
                0.0,
                0.0,
                0.0504991592097883,
                0.1650827814841407,
                0.010621175330271754,
                0.0,
                0.0,
                0.06342869488136296
            ],
            "[17, 1]": [
                0.11317632833651223,
                0.11172883277992787,
                0.14132121971188813,
                0.0,
                0.07000800474230387,
                0.0,
                0.0,
                0.024206799053725005,
                0.0,
                0.00476228776814587,
                0.0,
                0.0,
                0.0,
                0.0,
                0.0,
                0.0,
                0.013324186184089298,
                0.0,
                0.2924461402641555,
                0.0,
                0.0,
                0.0,
                0.08909854262420641,
                0.0,
                0.03159587279042691,
                0.0063260803034294495,
                0.0049927052053242525,
                0.0008186327504571924,
                0.09619436748540794
            ],
            "[18, 0]": [
                0.0,
                0.0,
                0.005571841730668891,
                0.16439292106462516,
                0.0,
                0.0,
                0.0,
                0.0,
                0.02478501491309067,
                0.0,
                0.0,
                0.0,
                0.014815511328337624,
                0.043781600396079895,
                0.03726379744885444,
                0.2015919957508316,
                0.0,
                0.030830131241795358,
                0.0198160175258376,
                0.017274691983028202,
                0.2296585713712551,
                0.0,
                0.04413407822479855,
                0.08727773183727842,
                0.0017514434332474085,
                0.0,
                0.07705465175027103,
                0.0,
                0.0
            ],
            "[18, 1]": [
                0.0,
                0.015788415589670896,
                0.0021574973415834716,
                0.0,
                0.04452061774590219,
                0.004030612710596984,
                0.0,
                0.6410136415418974,
                0.015246655932539535,
                0.009024261654505551,
                0.03291339710340567,
                0.0,
                0.013373951866549303,
                0.0,
                0.0029317654505765377,
                0.0443481181128702,
                0.05861233499922255,
                0.02364503152513711,
                0.0,
                0.027493475103508868,
                0.005976600896139853,
                0.0,
                0.0,
                0.014305744292901207,
                7.768896079042646e-05,
                0.015639092827047674,
                0.012615450535079526,
                0.016285645810075137,
                0.0
            ],
            "[19, 0]": [
                0.0009619170280053925,
                0.47811195030768594,
                0.0,
                0.0,
                0.0,
                0.006688193853375144,
                0.03512158858018912,
                0.006409647493433321,
                0.0,
                0.07672870402914715,
                0.03214608568802477,
                0.00012888575168666517,
                0.04399124915364158,
                0.0020405763825771224,
                0.04428450391191149,
                0.02546841941404906,
                0.06514376506165968,
                0.04322355662547319,
                0.0,
                0.0,
                0.0,
                0.055424190005906114,
                0.0,
                0.0,
                0.0349848806369271,
                0.0,
                0.039954346720294666,
                0.0,
                0.009187539356012419
            ],
            "[19, 1]": [
                0.04698584541044313,
                0.005248497456068773,
                0.0,
                0.022013570445724495,
                0.0,
                0.0,
                0.0,
                0.17260870742001044,
                0.0,
                0.0,
                0.0,
                0.0,
                0.0,
                0.11439900342730043,
                0.05984597449253632,
                0.0,
                0.0,
                0.055389652506640234,
                0.019770722770164263,
                0.0,
                0.24742929670562136,
                0.0,
                0.06765453629427574,
                0.0,
                0.0,
                0.045634707713877544,
                0.022389361251153955,
                0.10646520587829948,
                0.014164918227883804
            ],
            "[20, 0]": [
                0.0,
                0.0,
                0.1122496759019592,
                0.0,
                0.0,
                0.0,
                0.0,
                0.10845151550904358,
                0.04193740602274026,
                0.1020548701397788,
                0.027170067882513804,
                0.003826301493828575,
                0.0,
                0.35314248421199945,
                0.0,
                0.0,
                0.0,
                0.20507263366546002,
                0.0,
                0.0,
                0.028710656426102692,
                0.0,
                0.01549409588766209,
                0.0,
                0.0,
                0.0,
                0.0018902928589114218,
                0.0,
                0.0
            ],
            "[20, 1]": [
                0.0,
                0.05965124072899372,
                0.03148785344933904,
                0.02245678567348049,
                0.0,
                0.0,
                0.0,
                0.0420571266125008,
                0.020883800715950456,
                0.05920178902650719,
                0.11021904078591621,
                0.03248695310505318,
                0.18180901019057152,
                0.010624122766500325,
                0.0,
                0.0,
                0.0,
                0.04241737156180877,
                0.0536884668456685,
                0.10373880910518792,
                0.0,
                0.0,
                0.07137818108593433,
                0.0,
                0.005022227963937875,
                0.1364549346801618,
                0.0,
                0.016422285702487834,
                0.0
            ],
            "[21, 0]": [
                0.0,
                0.12943802915094635,
                0.0,
                0.0,
                0.0,
                0.00919140025932248,
                0.01752868612453402,
                0.0,
                0.2991399932926643,
                0.0,
                0.026749952518595944,
                0.01471894755421481,
                0.0449962330218161,
                0.13931726107815737,
                0.06916708422142179,
                0.03444786384028032,
                0.02309775735098429,
                0.0,
                0.0,
                0.0,
                0.0,
                0.0,
                0.002057721873300543,
                0.03613402490416049,
                0.11410366430762622,
                0.0,
                0.0,
                0.009042657468234648,
                0.030868723033740244
            ],
            "[21, 1]": [
                0.05355228080979817,
                0.003972646232935794,
                0.0,
                0.0,
                0.0,
                0.004655336387679571,
                0.03633123371749642,
                0.15941369407501954,
                0.03422706837894334,
                0.05757245761383077,
                0.0,
                0.0,
                0.0,
                0.03249367444672402,
                0.0,
                0.0,
                0.0,
                0.06751770113434719,
                0.011747761029762,
                0.0,
                0.0,
                0.0,
                0.05307200155164746,
                0.03300717690212618,
                0.037465471578681526,
                0.05325700331420356,
                0.0,
                0.3553961004896253,
                0.006318392337179234
            ],
            "[22, 0]": [
                0.07604367047424886,
                0.1310089254920232,
                0.21738763273432868,
                0.0,
                0.0,
                0.0,
                0.029469273908195783,
                0.024004351816333536,
                0.08217523259856142,
                0.0,
                0.0,
                0.011290104831489622,
                0.0,
                0.0,
                0.08103737084928858,
                0.0,
                0.0,
                0.0,
                0.0,
                0.20527687411979198,
                0.0,
                0.0799309841849268,
                0.0,
                0.0,
                0.0,
                0.0,
                0.026782181528767275,
                0.0,
                0.0355933974620444
            ],
            "[22, 1]": [
                0.04941146813830681,
                0.1855561453936447,
                0.0,
                0.06688396967535201,
                0.029197640515406405,
                0.013245768350818997,
                0.06042635543987369,
                0.16582483567605139,
                0.0,
                0.0,
                0.05441715786238565,
                0.0,
                0.0024821671705682067,
                0.0,
                0.0,
                0.039148146914179054,
                0.0,
                0.10396550664475178,
                0.0,
                0.00036333348331328075,
                0.006321948660637031,
                0.026051189344070247,
                0.0,
                0.0,
                0.0,
                0.0,
                0.009017572350978942,
                0.0,
                0.1876867943796618
            ],
            "[23, 0]": [
                0.002118347081320677,
                0.0,
                0.0,
                0.0016890959847088744,
                0.0,
                0.006721043270074125,
                0.0023796911971842227,
                0.003913564828691307,
                0.0004981133203811749,
                0.0,
                0.0,
                0.0,
                0.0,
                0.0,
                0.004177771187620403,
                0.0,
                0.0015520976391271359,
                0.003386834324898598,
                0.002039634983043821,
                0.016261938409497512,
                0.9458632636869662,
                0.00860665569700446,
                0.0,
                0.0004700447956888637,
                0.0,
                0.0003219035937925425,
                0.0,
                0.0,
                0.0
            ],
            "[23, 1]": [
                0.1523642995641255,
                0.01561852010465278,
                0.015226541721060234,
                0.20077463794254338,
                0.08467998920482933,
                0.04293432261353478,
                0.0,
                0.0,
                0.0,
                0.0,
                0.22450366685617162,
                0.09884850043814689,
                0.0,
                0.0,
                0.09071538060055291,
                0.0043910042059652305,
                0.0,
                0.024251738005953698,
                0.0193437699658614,
                0.0,
                0.0,
                0.0,
                0.0,
                0.0,
                0.0,
                0.026347628776602138,
                0.0,
                0.0,
                0.0
            ],
            "[24, 0]": [
                0.0008156631388785691,
                0.02552207753024753,
                0.0,
                0.0,
                0.0,
                0.0,
                0.0,
                0.0,
                0.0,
                0.0,
                0.0,
                0.02750245411633685,
                0.0,
                0.002804079871828273,
                0.01746412804984546,
                0.0,
                0.0,
                0.0,
                0.0,
                0.001282238421632619,
                0.0,
                0.018259649902982764,
                0.015381123241645842,
                0.042510712279411014,
                0.0,
                0.0345735198438009,
                0.0,
                0.031184929743871756,
                0.7826994238595184
            ],
            "[24, 1]": [
                0.0,
                0.0,
                0.0,
                0.038823474675968736,
                0.3089434658955987,
                0.0039295568694941285,
                0.12244471820384076,
                0.0,
                0.0,
                0.0,
                0.0,
                0.0,
                0.021050950714246123,
                0.0,
                0.11405853044683292,
                0.08194870333850147,
                0.028892433871379207,
                0.0,
                0.0,
                0.0,
                0.02934843979413093,
                0.0,
                0.0,
                0.09446091952813682,
                0.030233647540777592,
                0.014634014495250957,
                0.04910733546945649,
                0.0621238091563852,
                0.0
            ]
        }
    }
}